AUTHORS
LICENSE
MANIFEST.in
README.txt
setup.py
cjpy/__init__.py
cjpy/__main__.py
cjpy/cjson.py
cjpy/cmdscript.py
cjpy/example.py
cjpy/plottool.py
cjpy/tabletool.py
cjpy.egg-info/PKG-INFO
cjpy.egg-info/SOURCES.txt
cjpy.egg-info/dependency_links.txt
cjpy.egg-info/requires.txt
cjpy.egg-info/top_level.txt
cjpy/examples/example.py
cjpy/examples/input.json
cjpy/examples/iterations.json
cjpy/examples/manyfiles.json
cjpy/examples/onefile.json
cjpy/startup/cjpy.cmdline.json5
cjpy/startup/cjpy.mplot1d.json5
cjpy/startup/cjpy.scan_cols_plot1d.json5
cjpy/startup/cjpy.scan_hdus_plot1d.json5
cjpy/startup/example_aliases.sh
cjpy/startup/startup.json5