Metadata-Version: 2.1
Name: cjpy
Version: 0.3.6
Summary: Command liner with JSON based input file
Home-page: https://pypi.org/project/cjpy/0.3.6
Author: Jaesub Hong
Author-email: jhong@cfa.harvard.edu
License: UNKNOWN
Platform: UNKNOWN
Classifier: Programming Language :: Python :: 3
Classifier: License :: OSI Approved :: MIT License
Classifier: Operating System :: OS Independent
Requires-Python: >=3.5
